<?xml version="1.0" encoding="UTF-8"?>
<entity-engine-xml>

    <DynaScreenConfig dynaConfigId="CREATE_TASK_ACTIVITY_LEAD" componentMountPoint="activity-portal" layoutType="2C" isDisabled="N" securityGroupId="" createdBy="admin" defaultMessage="Task Activity - Configuration Not Found" lastModifiedBy="admin" isPrimary="Y" isFullscreen="" labelColSize="" inputColSize="" screenDisplayName="Task Activity" lastUpdatedStamp="2024-08-21 21:30:01.0" lastUpdatedTxStamp="2024-08-21 21:30:01.0" createdStamp="2021-08-08 07:17:07.0" createdTxStamp="2021-08-08 07:17:07.0"/>
    <DynaScreenConfigField dynaConfigId="CREATE_TASK_ACTIVITY_LEAD" dynaFieldId="actualCompletionDate" sequenceNum="21" isDisabled="N" fieldName="Actual End Date/Time" fieldType="DATE_TIME" fieldDataPattern="YYYY-MM-DD" isRequired="N" isCreate="N" isView="N" isEdit="N" lastUpdatedStamp="2024-08-21 21:30:01.0" lastUpdatedTxStamp="2024-08-21 21:30:01.0" createdStamp="2024-08-21 21:30:01.0" createdTxStamp="2024-08-21 21:30:01.0"/>
    <DynaScreenConfigField dynaConfigId="CREATE_TASK_ACTIVITY_LEAD" dynaFieldId="actualStartDate" sequenceNum="20" isDisabled="N" fieldName="Actual Start Date/Time" fieldType="DATE_TIME" fieldDataPattern="YYYY-MM-DD" isRequired="N" isCreate="N" isView="N" isEdit="N" lastUpdatedStamp="2024-08-21 21:30:01.0" lastUpdatedTxStamp="2024-08-21 21:30:01.0" createdStamp="2024-08-21 21:30:01.0" createdTxStamp="2024-08-21 21:30:01.0"/>
    <DynaScreenConfigField dynaConfigId="CREATE_TASK_ACTIVITY_LEAD" dynaFieldId="closedByUserLogin" sequenceNum="51" isDisabled="N" fieldName="Completed By" fieldType="TEXT" isRequired="N" isCreate="N" isView="Y" isEdit="N" lastUpdatedStamp="2024-08-21 21:30:01.0" lastUpdatedTxStamp="2024-08-21 21:30:01.0" createdStamp="2024-08-21 21:30:01.0" createdTxStamp="2024-08-21 21:30:01.0"/>
    <DynaScreenConfigField dynaConfigId="CREATE_TASK_ACTIVITY_LEAD" dynaFieldId="closedDateTime" sequenceNum="52" isDisabled="N" fieldName="Completed Date" fieldType="TEXT" isRequired="N" isCreate="N" isView="Y" isEdit="N" lastUpdatedStamp="2024-08-21 21:30:01.0" lastUpdatedTxStamp="2024-08-21 21:30:01.0" createdStamp="2024-08-21 21:30:01.0" createdTxStamp="2024-08-21 21:30:01.0"/>
    <DynaScreenConfigField dynaConfigId="CREATE_TASK_ACTIVITY_LEAD" dynaFieldId="contactId" sequenceNum="3" isDisabled="N" fieldName="Task Primary Contact" fieldType="DROPDOWN" lookupTypeId="CUSTOM" isRequired="Y" isCreate="Y" isView="Y" isEdit="Y" lastUpdatedStamp="2024-08-21 21:30:01.0" lastUpdatedTxStamp="2024-08-21 21:30:01.0" createdStamp="2024-08-21 21:30:01.0" createdTxStamp="2024-08-21 21:30:01.0"/>
    <DynaScreenConfigField dynaConfigId="CREATE_TASK_ACTIVITY_LEAD" dynaFieldId="createdDate" sequenceNum="13" isDisabled="N" fieldName="Created Date" fieldType="DATE" fieldDataPattern="YYYY-MM-DD" isRequired="N" isCreate="Y" isView="Y" isEdit="Y" lastUpdatedStamp="2024-08-21 21:30:01.0" lastUpdatedTxStamp="2024-08-21 21:30:01.0" createdStamp="2024-08-21 21:30:01.0" createdTxStamp="2024-08-21 21:30:01.0"/>
    <DynaScreenConfigField dynaConfigId="CREATE_TASK_ACTIVITY_LEAD" dynaFieldId="domainEntityId1" sequenceNum="31" isDisabled="Y" fieldName="Source ID" fieldType="TEXT" isRequired="N" isCreate="Y" isView="Y" isEdit="Y" lastUpdatedStamp="2024-08-21 21:30:01.0" lastUpdatedTxStamp="2024-08-21 21:30:01.0" createdStamp="2024-08-21 21:30:01.0" createdTxStamp="2024-08-21 21:30:01.0"/>
    <DynaScreenConfigField dynaConfigId="CREATE_TASK_ACTIVITY_LEAD" dynaFieldId="domainEntityType1" sequenceNum="30" isDisabled="Y" fieldName="Source Component" fieldType="TEXT" isRequired="N" isCreate="Y" isView="Y" isEdit="Y" lastUpdatedStamp="2024-08-21 21:30:01.0" lastUpdatedTxStamp="2024-08-21 21:30:01.0" createdStamp="2024-08-21 21:30:01.0" createdTxStamp="2024-08-21 21:30:01.0"/>
    <DynaScreenConfigField dynaConfigId="CREATE_TASK_ACTIVITY_LEAD" dynaFieldId="estimatedCompletionDate" sequenceNum="19" isDisabled="N" fieldName="Completed Date" fieldType="DATE" fieldDataPattern="YYYY-MM-DD" isRequired="N" isCreate="N" isView="Y" isEdit="Y" lastUpdatedStamp="2024-08-21 21:30:01.0" lastUpdatedTxStamp="2024-08-21 21:30:01.0" createdStamp="2024-08-21 21:30:01.0" createdTxStamp="2024-08-21 21:30:01.0"/>
    <DynaScreenConfigField dynaConfigId="CREATE_TASK_ACTIVITY_LEAD" dynaFieldId="estimatedStartDate" sequenceNum="18" isDisabled="N" fieldName="Sch.Start Date/Time" fieldType="DATE_TIME" fieldDataPattern="YYYY-MM-DD" isRequired="N" isCreate="N" isView="N" isEdit="N" lastUpdatedStamp="2024-08-21 21:30:01.0" lastUpdatedTxStamp="2024-08-21 21:30:01.0" createdStamp="2024-08-21 21:30:01.0" createdTxStamp="2024-08-21 21:30:01.0"/>
    <DynaScreenConfigField dynaConfigId="CREATE_TASK_ACTIVITY_LEAD" dynaFieldId="owner" sequenceNum="6" isDisabled="N" fieldName="Owners" fieldType="DROPDOWN" lookupTypeId="CUSTOM" isRequired="Y" isCreate="Y" isView="Y" isEdit="Y" lastUpdatedStamp="2024-08-21 21:30:01.0" lastUpdatedTxStamp="2024-08-21 21:30:01.0" createdStamp="2024-08-21 21:30:01.0" createdTxStamp="2024-08-21 21:30:01.0"/>
    <DynaScreenConfigField dynaConfigId="CREATE_TASK_ACTIVITY_LEAD" dynaFieldId="partyId" sequenceNum="50" isDisabled="N" fieldName="Dealer" fieldType="HIDDEN" isRequired="Y" isCreate="Y" isView="N" isEdit="Y" lastUpdatedStamp="2024-08-21 21:30:01.0" lastUpdatedTxStamp="2024-08-21 21:30:01.0" createdStamp="2024-08-21 21:30:01.0" createdTxStamp="2024-08-21 21:30:01.0"/>
    <DynaScreenConfigField dynaConfigId="CREATE_TASK_ACTIVITY_LEAD" dynaFieldId="priority" sequenceNum="8" isDisabled="N" fieldName="Task Priority" fieldType="DROPDOWN" lookupTypeId="DYNAMIC_DATA" lookupFieldService="dynaScreen.getDynamicData" lookupFieldFilter="{ 	&quot;entity_name&quot;: &quot;Enumeration&quot;, 	&quot;name_field&quot;: &quot;description&quot;, 	&quot;value_field&quot;: &quot;enumId&quot;, 	&quot;order_by&quot;: &quot;sequenceId&quot;, 	&quot;filter_value&quot;: { 		&quot;enumTypeId&quot;: &quot;PRIORITY_LEVEL&quot;, 		&quot;isEnabled&quot;: &quot;Y&quot; 	} }" isRequired="N" isCreate="Y" isView="Y" isEdit="Y" lastUpdatedStamp="2024-08-21 21:30:01.0" lastUpdatedTxStamp="2024-08-21 21:30:01.0" createdStamp="2024-08-21 21:30:01.0" createdTxStamp="2024-08-21 21:30:01.0"/>
    <DynaScreenConfigField dynaConfigId="CREATE_TASK_ACTIVITY_LEAD" dynaFieldId="statusId" sequenceNum="5" isDisabled="N" fieldName="Task Status" fieldType="DROPDOWN" lookupTypeId="DYNAMIC_DATA" lookupFieldService="dynaScreen.getDynamicData" lookupFieldFilter="{ 	&quot;entity_name&quot;: &quot;StatusItem&quot;, 	&quot;name_field&quot;: &quot;description&quot;, 	&quot;value_field&quot;: &quot;statusId&quot;, 	&quot;order_by&quot;: &quot;sequenceId&quot;, 	&quot;filter_value&quot;: { 		&quot;statusTypeId&quot;: &quot;IA_STATUS_ID&quot;, 		&quot;isEnabled&quot;: &quot;Y&quot; 	} }" isRequired="Y" isCreate="Y" isView="Y" isEdit="Y" defaultValue="IA_OPEN" lastUpdatedStamp="2024-08-21 21:30:01.0" lastUpdatedTxStamp="2024-08-21 21:30:01.0" createdStamp="2024-08-21 21:30:01.0" createdTxStamp="2024-08-21 21:30:01.0"/>
    <DynaScreenConfigField dynaConfigId="CREATE_TASK_ACTIVITY_LEAD" dynaFieldId="subject" sequenceNum="2" isDisabled="N" fieldName="Task Name" fieldType="TEXT" isRequired="Y" isCreate="Y" isView="Y" isEdit="Y" lastUpdatedStamp="2024-08-21 21:30:01.0" lastUpdatedTxStamp="2024-08-21 21:30:01.0" createdStamp="2024-08-21 21:30:01.0" createdTxStamp="2024-08-21 21:30:01.0"/>
    <DynaScreenConfigField dynaConfigId="CREATE_TASK_ACTIVITY_LEAD" dynaFieldId="timeZoneDesc" sequenceNum="20" isDisabled="N" fieldName="Time Zone" fieldType="DROPDOWN" lookupTypeId="DYNAMIC_DATA" lookupFieldService="dynaScreen.getDynamicData" lookupFieldFilter="{ 	&quot;entity_name&quot;: &quot;Enumeration&quot;, 	&quot;name_field&quot;: &quot;description&quot;, 	&quot;value_field&quot;: &quot;enumId&quot;, 	&quot;filter_value&quot;: { 		&quot;enumTypeId&quot;: &quot;TIME_ZONE&quot; 	} }" isRequired="N" isCreate="Y" isView="Y" isEdit="Y" lastUpdatedStamp="2024-08-21 21:30:01.0" lastUpdatedTxStamp="2024-08-21 21:30:01.0" createdStamp="2024-08-21 21:30:01.0" createdTxStamp="2024-08-21 21:30:01.0"/>
    <DynaScreenConfigField dynaConfigId="CREATE_TASK_ACTIVITY_LEAD" dynaFieldId="type" sequenceNum="1" isDisabled="N" fieldName="Activity Type" fieldType="TEXT" isRequired="Y" isCreate="Y" isView="N" isEdit="Y" lastUpdatedStamp="2024-08-21 21:30:01.0" lastUpdatedTxStamp="2024-08-21 21:30:01.0" createdStamp="2024-08-21 21:30:01.0" createdTxStamp="2024-08-21 21:30:01.0"/>
    <DynaScreenConfigField dynaConfigId="CREATE_TASK_ACTIVITY_LEAD" dynaFieldId="workEffortId" sequenceNum="2" isDisabled="Y" fieldName="Activity ID" fieldType="TEXT" isRequired="N" isCreate="N" isView="Y" isEdit="Y" lastUpdatedStamp="2024-08-21 21:30:01.0" lastUpdatedTxStamp="2024-08-21 21:30:01.0" createdStamp="2024-08-21 21:30:01.0" createdTxStamp="2024-08-21 21:30:01.0"/>
    <DynaScreenConfigField dynaConfigId="CREATE_TASK_ACTIVITY_LEAD" dynaFieldId="workEffortPurposeTypeId" sequenceNum="4" isDisabled="N" fieldName="Activity Work Type" fieldType="DROPDOWN" lookupTypeId="DYNAMIC_DATA" lookupFieldService="dynaScreen.getDynamicData" lookupFieldFilter="{ 	&quot;entity_name&quot;: &quot;WorkEffortPurposeType&quot;, 	&quot;name_field&quot;: &quot;description&quot;, 	&quot;value_field&quot;: &quot;workEffortPurposeTypeId&quot;, 	&quot;order_by&quot;: &quot;sequenceId&quot;,   	&quot;filter_value&quot;: { 		&quot;parentTypeId&quot;: &quot;ACTIVITY_WORK_TYPE&quot;, 		&quot;isEnabled&quot;: &quot;Y&quot;   	} }" isRequired="N" isCreate="Y" isView="Y" isEdit="Y" lastUpdatedStamp="2024-08-21 21:30:01.0" lastUpdatedTxStamp="2024-08-21 21:30:01.0" createdStamp="2024-08-21 21:30:01.0" createdTxStamp="2024-08-21 21:30:01.0"/>
    <DynaScreenConfigFieldAttribute dynaConfigId="CREATE_TASK_ACTIVITY_LEAD" dynaFieldId="contactId" attrName="isCreateDisplay" lastUpdatedStamp="2021-08-08 07:17:07.0" lastUpdatedTxStamp="2021-08-08 07:17:07.0" createdStamp="2021-08-08 07:17:07.0" createdTxStamp="2021-08-08 07:17:07.0"/>
    <DynaScreenConfigFieldAttribute dynaConfigId="CREATE_TASK_ACTIVITY_LEAD" dynaFieldId="contactId" attrName="isEditDisplay" lastUpdatedStamp="2021-08-08 07:17:07.0" lastUpdatedTxStamp="2021-08-08 07:17:07.0" createdStamp="2021-08-08 07:17:07.0" createdTxStamp="2021-08-08 07:17:07.0"/>
    <DynaScreenConfigFieldAttribute dynaConfigId="CREATE_TASK_ACTIVITY_LEAD" dynaFieldId="contactId" attrName="isLinkDisplay" attrValue="Y" lastUpdatedStamp="2021-08-08 07:17:07.0" lastUpdatedTxStamp="2021-08-08 07:17:07.0" createdStamp="2021-08-08 07:17:07.0" createdTxStamp="2021-08-08 07:17:07.0"/>
    <DynaScreenConfigFieldAttribute dynaConfigId="CREATE_TASK_ACTIVITY_LEAD" dynaFieldId="contactId" attrName="isMultiple" lastUpdatedStamp="2021-08-08 07:17:07.0" lastUpdatedTxStamp="2021-08-08 07:17:07.0" createdStamp="2021-08-08 07:17:07.0" createdTxStamp="2021-08-08 07:17:07.0"/>
    <DynaScreenConfigFieldAttribute dynaConfigId="CREATE_TASK_ACTIVITY_LEAD" dynaFieldId="domainEntityId1" attrName="isCreateDisplay" lastUpdatedStamp="2021-08-08 07:17:07.0" lastUpdatedTxStamp="2021-08-08 07:17:07.0" createdStamp="2021-08-08 07:17:07.0" createdTxStamp="2021-08-08 07:17:07.0"/>
    <DynaScreenConfigFieldAttribute dynaConfigId="CREATE_TASK_ACTIVITY_LEAD" dynaFieldId="domainEntityId1" attrName="isEditDisplay" lastUpdatedStamp="2021-08-08 07:17:07.0" lastUpdatedTxStamp="2021-08-08 07:17:07.0" createdStamp="2021-08-08 07:17:07.0" createdTxStamp="2021-08-08 07:17:07.0"/>
    <DynaScreenConfigFieldAttribute dynaConfigId="CREATE_TASK_ACTIVITY_LEAD" dynaFieldId="domainEntityId1" attrName="isLinkDisplay" attrValue="Y" lastUpdatedStamp="2021-08-08 07:17:07.0" lastUpdatedTxStamp="2021-08-08 07:17:07.0" createdStamp="2021-08-08 07:17:07.0" createdTxStamp="2021-08-08 07:17:07.0"/>
    <DynaScreenConfigFieldAttribute dynaConfigId="CREATE_TASK_ACTIVITY_LEAD" dynaFieldId="domainEntityId1" attrName="isPhoneNumber" lastUpdatedStamp="2021-08-08 07:17:07.0" lastUpdatedTxStamp="2021-08-08 07:17:07.0" createdStamp="2021-08-08 07:17:07.0" createdTxStamp="2021-08-08 07:17:07.0"/>
    <DynaScreenConfigFieldAttribute dynaConfigId="CREATE_TASK_ACTIVITY_LEAD" dynaFieldId="owner" attrName="isCreateDisplay" lastUpdatedStamp="2021-08-08 07:17:07.0" lastUpdatedTxStamp="2021-08-08 07:17:07.0" createdStamp="2021-08-08 07:17:07.0" createdTxStamp="2021-08-08 07:17:07.0"/>
    <DynaScreenConfigFieldAttribute dynaConfigId="CREATE_TASK_ACTIVITY_LEAD" dynaFieldId="owner" attrName="isEditDisplay" lastUpdatedStamp="2021-08-08 07:17:07.0" lastUpdatedTxStamp="2021-08-08 07:17:07.0" createdStamp="2021-08-08 07:17:07.0" createdTxStamp="2021-08-08 07:17:07.0"/>
    <DynaScreenConfigFieldAttribute dynaConfigId="CREATE_TASK_ACTIVITY_LEAD" dynaFieldId="owner" attrName="isLinkDisplay" lastUpdatedStamp="2021-08-08 07:17:07.0" lastUpdatedTxStamp="2021-08-08 07:17:07.0" createdStamp="2021-08-08 07:17:07.0" createdTxStamp="2021-08-08 07:17:07.0"/>
    <DynaScreenConfigFieldAttribute dynaConfigId="CREATE_TASK_ACTIVITY_LEAD" dynaFieldId="owner" attrName="isMultiple" attrValue="Y" lastUpdatedStamp="2021-08-08 07:17:07.0" lastUpdatedTxStamp="2021-08-08 07:17:07.0" createdStamp="2021-08-08 07:17:07.0" createdTxStamp="2021-08-08 07:17:07.0"/>
 
	<DynaScreenConfig dynaConfigId="CREATE_DYNA_SCREEN" componentMountPoint="admin-portal" layoutType="2C" isDisabled="N" securityGroupId="" createdBy="admin" defaultMessage="screen configuration in-progress" lastModifiedBy="admin" isPrimary="" isFullscreen="Y" labelColSize="col-sm-4" inputColSize="col-sm-8" screenDisplayName="Create/Update Dyna Screen" lastUpdatedStamp="2024-07-08 11:58:44.0" lastUpdatedTxStamp="2024-07-08 11:58:44.0" createdStamp="2024-07-08 11:14:01.0" createdTxStamp="2024-07-08 11:14:01.0"/>
	<DynaScreenConfigField dynaConfigId="CREATE_DYNA_SCREEN" dynaFieldId="componentMountPoint" sequenceNum="2" isDisabled="N" fieldName="Module" fieldType="DROPDOWN" lookupTypeId="DYNAMIC_DATA" lookupFieldService="dynaScreen.getDynamicData" lookupFieldFilter="	  { 	&quot;entity_name&quot;: &quot;OfbizComponentAccess&quot;, 	&quot;name_field&quot;: &quot;description&quot;, 	&quot;value_field&quot;: &quot;componentName&quot; , &quot;filter_value&quot;: {  &quot;isHide&quot;: &quot;N&quot; }}" isRequired="N" isCreate="Y" isView="Y" isEdit="Y" lastUpdatedStamp="2024-07-08 11:58:44.0" lastUpdatedTxStamp="2024-07-08 11:58:44.0" createdStamp="2024-07-08 11:58:44.0" createdTxStamp="2024-07-08 11:58:44.0"/>
    <DynaScreenConfigField dynaConfigId="CREATE_DYNA_SCREEN" dynaFieldId="defaultMessage" sequenceNum="6" isDisabled="N" fieldName="Default Message" fieldType="TEXT" isRequired="N" isCreate="Y" isView="Y" isEdit="Y" lastUpdatedStamp="2024-07-08 11:58:44.0" lastUpdatedTxStamp="2024-07-08 11:58:44.0" createdStamp="2024-07-08 11:58:44.0" createdTxStamp="2024-07-08 11:58:44.0"/>
    <DynaScreenConfigField dynaConfigId="CREATE_DYNA_SCREEN" dynaFieldId="fromDate" sequenceNum="9" isDisabled="N" fieldName="FromDate" fieldType="DATE" fieldDataPattern="DD/MM/YYYY" isRequired="N" isCreate="Y" isView="Y" isEdit="Y" lastUpdatedStamp="2024-07-08 11:58:44.0" lastUpdatedTxStamp="2024-07-08 11:58:44.0" createdStamp="2024-07-08 11:58:44.0" createdTxStamp="2024-07-08 11:58:44.0"/>
    <DynaScreenConfigField dynaConfigId="CREATE_DYNA_SCREEN" dynaFieldId="inputColSize" sequenceNum="8" isDisabled="N" fieldName="Input Column Size" fieldType="DROPDOWN" lookupTypeId="DYNAMIC_DATA" lookupFieldService="dynaScreen.getDynamicData" lookupFieldFilter="{ 	&quot;entity_name&quot;: &quot;Enumeration&quot;, 	&quot;name_field&quot;: &quot;description&quot;, 	&quot;value_field&quot;: &quot;enumId&quot;, 	&quot;filter_value&quot;: { &quot;enumTypeId&quot;: &quot;COLUMN_SIZE&quot; } }" isRequired="N" isCreate="Y" isView="Y" isEdit="Y" lastUpdatedStamp="2024-07-08 11:58:44.0" lastUpdatedTxStamp="2024-07-08 11:58:44.0" createdStamp="2024-07-08 11:58:44.0" createdTxStamp="2024-07-08 11:58:44.0"/>
    <DynaScreenConfigField dynaConfigId="CREATE_DYNA_SCREEN" dynaFieldId="instanceId" sequenceNum="1" isDisabled="N" fieldName="Instance Id" fieldType="TEXT" isRequired="N" isCreate="Y" isView="Y" isEdit="Y" lastUpdatedStamp="2024-07-08 11:58:44.0" lastUpdatedTxStamp="2024-07-08 11:58:44.0" createdStamp="2024-07-08 11:58:44.0" createdTxStamp="2024-07-08 11:58:44.0"/>
    <DynaScreenConfigField dynaConfigId="CREATE_DYNA_SCREEN" dynaFieldId="isDisabledDyna" sequenceNum="12" isDisabled="N" fieldName="Is Disabled" fieldType="DROPDOWN" lookupTypeId="DYNAMIC_DATA" lookupFieldService="dynaScreen.getDynamicData" lookupFieldFilter="{ 	&quot;entity_name&quot;: &quot;Enumeration&quot;, 	&quot;name_field&quot;: &quot;description&quot;, 	&quot;value_field&quot;: &quot;enumCode&quot;, 	&quot;filter_value&quot;: { &quot;enumTypeId&quot;: &quot;INDICATOR_TYPE&quot; } }" isRequired="N" isCreate="Y" isView="Y" isEdit="Y" lastUpdatedStamp="2024-07-08 11:58:44.0" lastUpdatedTxStamp="2024-07-08 11:58:44.0" createdStamp="2024-07-08 11:58:44.0" createdTxStamp="2024-07-08 11:58:44.0"/>
    <DynaScreenConfigField dynaConfigId="CREATE_DYNA_SCREEN" dynaFieldId="isFullscreen" sequenceNum="13" isDisabled="N" fieldName="Is Full Screen" fieldType="DROPDOWN" lookupTypeId="DYNAMIC_DATA" lookupFieldService="dynaScreen.getDynamicData" lookupFieldFilter="{ 	&quot;entity_name&quot;: &quot;Enumeration&quot;, 	&quot;name_field&quot;: &quot;description&quot;, 	&quot;value_field&quot;: &quot;enumCode&quot;, 	&quot;filter_value&quot;: { &quot;enumTypeId&quot;: &quot;INDICATOR_TYPE&quot; } }" isRequired="N" isCreate="Y" isView="Y" isEdit="Y" lastUpdatedStamp="2024-07-08 11:58:44.0" lastUpdatedTxStamp="2024-07-08 11:58:44.0" createdStamp="2024-07-08 11:58:44.0" createdTxStamp="2024-07-08 11:58:44.0"/>
    <DynaScreenConfigField dynaConfigId="CREATE_DYNA_SCREEN" dynaFieldId="isPrimary" sequenceNum="11" isDisabled="N" fieldName="Is Primary" fieldType="DROPDOWN" lookupTypeId="DYNAMIC_DATA" lookupFieldService="dynaScreen.getDynamicData" lookupFieldFilter="{ 	&quot;entity_name&quot;: &quot;Enumeration&quot;, 	&quot;name_field&quot;: &quot;description&quot;, 	&quot;value_field&quot;: &quot;enumCode&quot;, 	&quot;filter_value&quot;: { &quot;enumTypeId&quot;: &quot;INDICATOR_TYPE&quot; } }" isRequired="N" isCreate="Y" isView="Y" isEdit="Y" lastUpdatedStamp="2024-07-08 11:58:44.0" lastUpdatedTxStamp="2024-07-08 11:58:44.0" createdStamp="2024-07-08 11:58:44.0" createdTxStamp="2024-07-08 11:58:44.0"/>
    <DynaScreenConfigField dynaConfigId="CREATE_DYNA_SCREEN" dynaFieldId="labelColSize" sequenceNum="7" isDisabled="N" fieldName="Label Column Size" fieldType="DROPDOWN" lookupTypeId="DYNAMIC_DATA" lookupFieldService="dynaScreen.getDynamicData" lookupFieldFilter="{ 	&quot;entity_name&quot;: &quot;Enumeration&quot;, 	&quot;name_field&quot;: &quot;description&quot;, 	&quot;value_field&quot;: &quot;enumId&quot;, 	&quot;filter_value&quot;: { &quot;enumTypeId&quot;: &quot;COLUMN_SIZE&quot; } }" isRequired="N" isCreate="Y" isView="Y" isEdit="Y" lastUpdatedStamp="2024-07-08 11:58:44.0" lastUpdatedTxStamp="2024-07-08 11:58:44.0" createdStamp="2024-07-08 11:58:44.0" createdTxStamp="2024-07-08 11:58:44.0"/>
    <DynaScreenConfigField dynaConfigId="CREATE_DYNA_SCREEN" dynaFieldId="layoutType" sequenceNum="4" isDisabled="N" fieldName="Layout Type" fieldType="DROPDOWN" lookupTypeId="DYNAMIC_DATA" lookupFieldService="dynaScreen.getDynamicData" lookupFieldFilter="{ 	&quot;entity_name&quot;: &quot;Enumeration&quot;, 	&quot;name_field&quot;: &quot;description&quot;, 	&quot;value_field&quot;: &quot;enumCode&quot;, 	&quot;filter_value&quot;: { &quot;enumTypeId&quot;: &quot;LAYOUT_TYPE&quot; } }" isRequired="Y" isCreate="Y" isView="Y" isEdit="Y" lastUpdatedStamp="2024-07-08 11:58:44.0" lastUpdatedTxStamp="2024-07-08 11:58:44.0" createdStamp="2024-07-08 11:58:44.0" createdTxStamp="2024-07-08 11:58:44.0"/>
    <DynaScreenConfigField dynaConfigId="CREATE_DYNA_SCREEN" dynaFieldId="screenDisplayName" sequenceNum="3" isDisabled="N" fieldName="Display Name" fieldType="TEXT" isRequired="Y" isCreate="Y" isView="Y" isEdit="Y" lastUpdatedStamp="2024-07-08 11:58:44.0" lastUpdatedTxStamp="2024-07-08 11:58:44.0" createdStamp="2024-07-08 11:58:44.0" createdTxStamp="2024-07-08 11:58:44.0"/>
    <DynaScreenConfigField dynaConfigId="CREATE_DYNA_SCREEN" dynaFieldId="securityGroupId" sequenceNum="5" isDisabled="N" fieldName="Security Group" fieldType="DROPDOWN" lookupTypeId="DYNAMIC_DATA" lookupFieldService="dynaScreen.getDynamicData" lookupFieldFilter="{ 	&quot;entity_name&quot;: &quot;SecurityGroup&quot;, 	&quot;name_field&quot;: &quot;description&quot;, 	&quot;value_field&quot;: &quot;groupId&quot; }" isRequired="N" isCreate="Y" isView="Y" isEdit="Y" lastUpdatedStamp="2024-07-08 11:58:44.0" lastUpdatedTxStamp="2024-07-08 11:58:44.0" createdStamp="2024-07-08 11:58:44.0" createdTxStamp="2024-07-08 11:58:44.0"/>
    <DynaScreenConfigField dynaConfigId="CREATE_DYNA_SCREEN" dynaFieldId="thruDate" sequenceNum="10" isDisabled="N" fieldName="thru Date" fieldType="DATE" fieldDataPattern="DD/MM/YYYY" isRequired="N" isCreate="Y" isView="Y" isEdit="Y" lastUpdatedStamp="2024-07-08 11:58:44.0" lastUpdatedTxStamp="2024-07-08 11:58:44.0" createdStamp="2024-07-08 11:58:44.0" createdTxStamp="2024-07-08 11:58:44.0"/>
	<DynaScreenConfigFieldAttribute dynaConfigId="CREATE_DYNA_SCREEN" dynaFieldId="instanceId" attrName="isCreateDisplay" attrValue="N" lastUpdatedStamp="2024-07-08 11:56:25.0" lastUpdatedTxStamp="2024-07-08 11:56:25.0" createdStamp="2024-07-08 11:52:40.0" createdTxStamp="2024-07-08 11:52:40.0"/>
    <DynaScreenConfigFieldAttribute dynaConfigId="CREATE_DYNA_SCREEN" dynaFieldId="instanceId" attrName="isEditDisplay" attrValue="Y" lastUpdatedStamp="2024-07-08 11:56:25.0" lastUpdatedTxStamp="2024-07-08 11:56:25.0" createdStamp="2024-07-08 11:52:40.0" createdTxStamp="2024-07-08 11:52:40.0"/>
    <DynaScreenConfigFieldAttribute dynaConfigId="CREATE_DYNA_SCREEN" dynaFieldId="instanceId" attrName="isLinkDisplay" attrValue="" lastUpdatedStamp="2024-07-08 11:56:25.0" lastUpdatedTxStamp="2024-07-08 11:56:25.0" createdStamp="2024-07-08 11:52:40.0" createdTxStamp="2024-07-08 11:52:40.0"/>
    <DynaScreenConfigFieldAttribute dynaConfigId="CREATE_DYNA_SCREEN" dynaFieldId="instanceId" attrName="isPhoneNumber" attrValue="" lastUpdatedStamp="2024-07-08 11:56:25.0" lastUpdatedTxStamp="2024-07-08 11:56:25.0" createdStamp="2024-07-08 11:52:40.0" createdTxStamp="2024-07-08 11:52:40.0"/>
    <DynaScreenConfigFieldAttribute dynaConfigId="CREATE_DYNA_SCREEN" dynaFieldId="instanceId" attrName="placeholder" attrValue="" lastUpdatedStamp="2024-07-08 11:56:25.0" lastUpdatedTxStamp="2024-07-08 11:56:25.0" createdStamp="2024-07-08 11:52:40.0" createdTxStamp="2024-07-08 11:52:40.0"/>
	
	<DynaScreenConfig dynaConfigId="FIND_DYNA_SCREEN" componentMountPoint="admin-portal" layoutType="2C" isDisabled="N" securityGroupId="" createdBy="admin" defaultMessage="screen configuration in-progress" lastModifiedBy="admin" isPrimary="Y" isFullscreen="Y" labelColSize="col-sm-4" inputColSize="col-sm-8" screenDisplayName="Find Screen Configurations" lastUpdatedStamp="2024-07-05 21:11:48.0" lastUpdatedTxStamp="2024-07-05 21:11:48.0" createdStamp="2024-07-05 19:22:44.0" createdTxStamp="2024-07-05 19:22:44.0"/>
	<DynaScreenConfigField dynaConfigId="FIND_DYNA_SCREEN" dynaFieldId="componentMountPoint" sequenceNum="5" isDisabled="N" fieldName="Components" fieldType="DROPDOWN" lookupTypeId="DYNAMIC_DATA" lookupFieldService="dynaScreen.getDynamicData" lookupFieldFilter="	  { 	&quot;entity_name&quot;: &quot;OfbizComponentAccess&quot;, 	&quot;name_field&quot;: &quot;description&quot;, 	&quot;value_field&quot;: &quot;componentName&quot; , &quot;filter_value&quot;: {  &quot;isHide&quot;: &quot;N&quot; }}" isRequired="N" isCreate="Y" isView="Y" isEdit="Y" lastUpdatedStamp="2024-07-05 21:11:48.0" lastUpdatedTxStamp="2024-07-05 21:11:48.0" createdStamp="2024-07-05 21:11:48.0" createdTxStamp="2024-07-05 21:11:48.0"/>
    <DynaScreenConfigField dynaConfigId="FIND_DYNA_SCREEN" dynaFieldId="dynaConfigId" sequenceNum="1" isDisabled="N" fieldName="Dyna Config Id" fieldType="TEXT" isRequired="N" isCreate="Y" isView="Y" isEdit="Y" lastUpdatedStamp="2024-07-05 21:11:48.0" lastUpdatedTxStamp="2024-07-05 21:11:48.0" createdStamp="2024-07-05 21:11:48.0" createdTxStamp="2024-07-05 21:11:48.0"/>
    <DynaScreenConfigField dynaConfigId="FIND_DYNA_SCREEN" dynaFieldId="isPrimary" sequenceNum="4" isDisabled="N" fieldName="Is Primary" fieldType="DROPDOWN" lookupTypeId="DYNAMIC_DATA" lookupFieldService="dynaScreen.getDynamicData" lookupFieldFilter="{ 	&quot;entity_name&quot;: &quot;Enumeration&quot;, 	&quot;name_field&quot;: &quot;description&quot;, 	&quot;value_field&quot;: &quot;enumCode&quot;, 	&quot;filter_value&quot;: { &quot;enumTypeId&quot;: &quot;INDICATOR_TYPE&quot; } }" isRequired="N" isCreate="Y" isView="Y" isEdit="Y" lastUpdatedStamp="2024-07-05 21:11:48.0" lastUpdatedTxStamp="2024-07-05 21:11:48.0" createdStamp="2024-07-05 21:11:48.0" createdTxStamp="2024-07-05 21:11:48.0"/>
    <DynaScreenConfigField dynaConfigId="FIND_DYNA_SCREEN" dynaFieldId="layoutType" sequenceNum="3" isDisabled="N" fieldName="Layout Type" fieldType="DROPDOWN" lookupTypeId="DYNAMIC_DATA" lookupFieldService="dynaScreen.getDynamicData" lookupFieldFilter="{ 	&quot;entity_name&quot;: &quot;Enumeration&quot;, 	&quot;name_field&quot;: &quot;description&quot;, 	&quot;value_field&quot;: &quot;enumCode&quot;, 	&quot;filter_value&quot;: { &quot;enumTypeId&quot;: &quot;LAYOUT_TYPE&quot; } }" isRequired="N" isCreate="Y" isView="Y" isEdit="Y" lastUpdatedStamp="2024-07-05 21:11:48.0" lastUpdatedTxStamp="2024-07-05 21:11:48.0" createdStamp="2024-07-05 21:11:48.0" createdTxStamp="2024-07-05 21:11:48.0"/>
    <DynaScreenConfigField dynaConfigId="FIND_DYNA_SCREEN" dynaFieldId="screenDisplayName" sequenceNum="2" isDisabled="N" fieldName="Dyna Name" fieldType="TEXT" isRequired="N" isCreate="Y" isView="Y" isEdit="Y" lastUpdatedStamp="2024-07-05 21:11:48.0" lastUpdatedTxStamp="2024-07-05 21:11:48.0" createdStamp="2024-07-05 21:11:48.0" createdTxStamp="2024-07-05 21:11:48.0"/>
	
    <EnumerationType enumTypeId="LAYOUT_TYPE" hasTable="N" description="Layout type for dyna" lastUpdatedStamp="2023-12-06 15:13:49.0" lastUpdatedTxStamp="2023-12-06 15:13:48.0" createdStamp="2023-12-06 15:13:49.0" createdTxStamp="2023-12-06 15:13:48.0"/>
    <Enumeration enumId="1C" enumTypeId="LAYOUT_TYPE" enumCode="1C" sequenceId="1" description="One Column" lastUpdatedStamp="2024-07-05 20:45:13.0" lastUpdatedTxStamp="2024-07-05 20:45:13.0" createdStamp="2024-07-05 20:45:13.0" createdTxStamp="2024-07-05 20:45:13.0" name="One Column"/>
    <Enumeration enumId="2C" enumTypeId="LAYOUT_TYPE" enumCode="2C" sequenceId="2" description="Two Column" lastUpdatedStamp="2024-07-05 20:45:13.0" lastUpdatedTxStamp="2024-07-05 20:45:13.0" createdStamp="2024-07-05 20:45:13.0" createdTxStamp="2024-07-05 20:45:13.0" name="Two Column"/>
    <Enumeration enumId="3C" enumTypeId="LAYOUT_TYPE" enumCode="3C" sequenceId="3" description="Three Column" lastUpdatedStamp="2024-07-05 20:45:13.0" lastUpdatedTxStamp="2024-07-05 20:45:13.0" createdStamp="2024-07-05 20:45:13.0" createdTxStamp="2024-07-05 20:45:13.0" name="Three Column"/>

    <EnumerationType enumTypeId="COLUMN_SIZE" hasTable="N" description="Column Size" lastUpdatedStamp="2023-12-06 15:13:49.0" lastUpdatedTxStamp="2023-12-06 15:13:48.0" createdStamp="2023-12-06 15:13:49.0" createdTxStamp="2023-12-06 15:13:48.0"/>

	<Enumeration enumId="col-sm-1" enumTypeId="COLUMN_SIZE" enumCode="col-sm-1" sequenceId="1" description="col-sm-1" lastUpdatedStamp="2023-12-06 15:13:52.0" lastUpdatedTxStamp="2023-12-06 15:13:48.0" createdStamp="2023-12-06 15:13:52.0" createdTxStamp="2023-12-06 15:13:48.0" name="col-sm-1"/>
    <Enumeration enumId="col-sm-10" enumTypeId="COLUMN_SIZE" enumCode="col-sm-10" sequenceId="10" description="col-sm-10" lastUpdatedStamp="2023-12-06 15:13:52.0" lastUpdatedTxStamp="2023-12-06 15:13:48.0" createdStamp="2023-12-06 15:13:52.0" createdTxStamp="2023-12-06 15:13:48.0" name="col-sm-10"/>
    <Enumeration enumId="col-sm-2" enumTypeId="COLUMN_SIZE" enumCode="col-sm-2" sequenceId="2" description="col-sm-2" lastUpdatedStamp="2023-12-06 15:13:52.0" lastUpdatedTxStamp="2023-12-06 15:13:48.0" createdStamp="2023-12-06 15:13:52.0" createdTxStamp="2023-12-06 15:13:48.0" name="col-sm-2"/>
    <Enumeration enumId="col-sm-3" enumTypeId="COLUMN_SIZE" enumCode="col-sm-3" sequenceId="3" description="col-sm-3" lastUpdatedStamp="2023-12-06 15:13:52.0" lastUpdatedTxStamp="2023-12-06 15:13:48.0" createdStamp="2023-12-06 15:13:52.0" createdTxStamp="2023-12-06 15:13:48.0" name="col-sm-3"/>
    <Enumeration enumId="col-sm-4" enumTypeId="COLUMN_SIZE" enumCode="col-sm-4" sequenceId="4" description="col-sm-4" lastUpdatedStamp="2023-12-06 15:13:52.0" lastUpdatedTxStamp="2023-12-06 15:13:48.0" createdStamp="2023-12-06 15:13:52.0" createdTxStamp="2023-12-06 15:13:48.0" name="col-sm-4"/>
    <Enumeration enumId="col-sm-5" enumTypeId="COLUMN_SIZE" enumCode="col-sm-5" sequenceId="5" description="col-sm-5" lastUpdatedStamp="2023-12-06 15:13:52.0" lastUpdatedTxStamp="2023-12-06 15:13:48.0" createdStamp="2023-12-06 15:13:52.0" createdTxStamp="2023-12-06 15:13:48.0" name="col-sm-5"/>
    <Enumeration enumId="col-sm-6" enumTypeId="COLUMN_SIZE" enumCode="col-sm-6" sequenceId="6" description="col-sm-6" lastUpdatedStamp="2023-12-06 15:13:52.0" lastUpdatedTxStamp="2023-12-06 15:13:48.0" createdStamp="2023-12-06 15:13:52.0" createdTxStamp="2023-12-06 15:13:48.0" name="col-sm-6"/>
    <Enumeration enumId="col-sm-7" enumTypeId="COLUMN_SIZE" enumCode="col-sm-7" sequenceId="7" description="col-sm-7" lastUpdatedStamp="2023-12-06 15:13:52.0" lastUpdatedTxStamp="2023-12-06 15:13:48.0" createdStamp="2023-12-06 15:13:52.0" createdTxStamp="2023-12-06 15:13:48.0" name="col-sm-7"/>
    <Enumeration enumId="col-sm-8" enumTypeId="COLUMN_SIZE" enumCode="col-sm-8" sequenceId="8" description="col-sm-8" lastUpdatedStamp="2023-12-06 15:13:52.0" lastUpdatedTxStamp="2023-12-06 15:13:48.0" createdStamp="2023-12-06 15:13:52.0" createdTxStamp="2023-12-06 15:13:48.0" name="col-sm-8"/>
    <Enumeration enumId="col-sm-9" enumTypeId="COLUMN_SIZE" enumCode="col-sm-9" sequenceId="9" description="col-sm-9" lastUpdatedStamp="2023-12-06 15:13:52.0" lastUpdatedTxStamp="2023-12-06 15:13:48.0" createdStamp="2023-12-06 15:13:52.0" createdTxStamp="2023-12-06 15:13:48.0" name="col-sm-9"/>
 
 	<AppBarType appBarTypeId="ACTION" appBarTypeName="Action App Bar" appBarTypeUilabel="Action App Bar" lastUpdatedStamp="2020-07-06 15:39:43.0" lastUpdatedTxStamp="2020-07-06 15:39:43.0" createdStamp="2020-07-06 15:39:43.0" createdTxStamp="2020-07-06 15:39:43.0"/>
  	<AppBar appBarId="ACTION_APP_BAR" appBarTypeId="ACTION" appBarName="Action bar" appBarNameUilabel="Action bar" appBarDescription="Action bar" appBarService="" appBarStatus="ENABLED" appBarSecurityGroup="ACTION_APP_BAR_GRP" appBarDirection="HORIZONTAL" appBarHeight="100" appBarWidth="100" appBarMaxElements="20" appBarAccessLevel="SYSTEM_LEVEL" appBarDataLevel="" appBarIsServiceBased="" createdBy="admin" modifiedBy="admin" approvedBy="admin" approvedDate="2020-07-06 15:50:54" autoApprove="" createdOn="2020-07-06 15:50:54" modifiedOn="2022-09-19 11:33:07" geoId="" appBarRefreshType="" appBarRefreshMinRate="" defaultMessage="" lastUpdatedStamp="2022-09-19 11:33:07" createdTxStamp="2020-07-06 15:50:54" lastUpdatedTxStamp="2022-09-19 11:33:07" createdStamp="2020-07-06 15:50:54"/>
  	<AppBarElements appBarElementActive="Y" appBarElementCustomClass="text-dark left-icones" appBarElementFavIcon="fa fa-plus-square custicons" appBarElementId="E10005" appBarElementName="Add Service Request" appBarElementPosition="L" appBarElementSeqNum="6" appBarElementTargetUrl="/ticket-portal/control/addservicerequest?partyId=${partyId}&amp;externalLoginKey=${externalLoginKey}" appBarElementType="LINK" appBarElementUilabel="Add Service Request" appBarId="ACTION_APP_BAR" appBarTypeId="ACTION" approvedDate="2020-06-24 19:11:44.0" createdBy="admin" createdOn="2020-06-24 19:11:44.0" createdStamp="2020-06-24 19:11:44.0" createdTxStamp="2020-06-24 19:11:44.0" elementKey="addServiceRequest" isApprovedBy="admin" isDisplayElementData="N" lastUpdatedStamp="2024-08-27 14:07:19.0" lastUpdatedTxStamp="2024-08-27 14:07:19.0" modifiedBy="anand" modifiedOn="2020-10-10 11:44:23.0" securityPermissionId="ACTION_PERMISSION"/>
 
</entity-engine-xml>