<?xml version="1.0" encoding="UTF-8"?>
<entity-engine-xml>

	<SystemProperty systemResourceId="general" systemPropertyId="general.sftp.host" systemPropertyValue="172.31.6.72" lastUpdatedStamp="2022-11-03 02:33:18.0" lastUpdatedTxStamp="2022-11-03 02:33:18.0"/>
    <SystemProperty systemResourceId="general" systemPropertyId="general.sftp.location" systemPropertyValue="/home/icrmbaseftp1/11" lastUpdatedStamp="2022-11-03 02:33:18.0" lastUpdatedTxStamp="2022-11-03 02:33:18.0"/>
    <SystemProperty systemResourceId="general" systemPropertyId="general.sftp.password" systemPropertyValue="!crmftpbase@12345" lastUpdatedStamp="2022-11-03 02:33:18.0" lastUpdatedTxStamp="2022-11-03 02:33:18.0"/>
    <SystemProperty systemResourceId="general" systemPropertyId="general.sftp.port" systemPropertyValue="2200" lastUpdatedStamp="2022-11-03 02:33:18.0" lastUpdatedTxStamp="2022-11-03 02:33:18.0"/>
    <SystemProperty systemResourceId="general" systemPropertyId="general.sftp.user" systemPropertyValue="icrmbaseftp" lastUpdatedStamp="2022-11-03 02:33:18.0" lastUpdatedTxStamp="2022-11-03 02:33:18.0"/>

	<SftpConfiguration seqId="attribute-default" userName="dbsfio" password="FIO#DBS@123" port="22" host="35.185.64.191" lastUpdatedStamp="2018-07-03 15:40:07.0" lastUpdatedTxStamp="2018-07-03 15:40:07.0" createdStamp="2018-07-03 15:40:07.0" createdTxStamp="2018-07-03 15:40:07.0" enable="Y" modelName="ATTRIBUTE" location="/home/dbsfio/attribute-importfiles"/>
    <SftpConfiguration seqId="contactListUpload" userName="icrmsitsftp" password="fio@123456" port="2232" host="146.88.24.72" lastUpdatedStamp="2018-07-03 15:40:07.0" lastUpdatedTxStamp="2018-07-03 15:40:07.0" createdStamp="2018-07-03 15:40:07.0" createdTxStamp="2018-07-03 15:40:07.0" enable="Y" modelName="UPLOADLIST" location="/"/>

	<SystemProperty systemResourceId="general" systemPropertyId="api-key" systemPropertyValue="fioicrmapi" description="API Key" lastUpdatedStamp="2018-06-01 10:16:56.0" lastUpdatedTxStamp="2018-06-01 10:16:56.0" createdStamp="2018-06-01 10:16:56.0" createdTxStamp="2018-06-01 10:16:56.0"/>
    <SystemProperty systemResourceId="general" systemPropertyId="api-key-auth" systemPropertyValue="Y" lastUpdatedStamp="2022-11-14 23:04:02.0" lastUpdatedTxStamp="2022-11-14 23:04:02.0" createdStamp="2022-11-14 23:04:02.0" createdTxStamp="2022-11-14 23:04:02.0"/>
    <SystemProperty systemResourceId="general" systemPropertyId="country.geo.id.default" description="the default country for drop downs" lastUpdatedStamp="2018-06-01 10:16:56.0" lastUpdatedTxStamp="2018-06-01 10:16:56.0" createdStamp="2018-06-01 10:16:56.0" createdTxStamp="2018-06-01 10:16:56.0"/>
    <SystemProperty systemResourceId="general" systemPropertyId="currency.uom.id.default" description="The default currency to use for prices, etc" lastUpdatedStamp="2018-06-01 10:16:56.0" lastUpdatedTxStamp="2018-06-01 10:16:56.0" createdStamp="2018-06-01 10:16:56.0" createdTxStamp="2018-06-01 10:16:56.0"/>
    <SystemProperty systemResourceId="general" systemPropertyId="defaultFromEmailAddress" systemPropertyValue="no-reply@groupfio.com" description="general default &apos;fromEmailAddress&apos; can be overridden in: EmailTemplateSetting" lastUpdatedStamp="2018-06-01 10:16:56.0" lastUpdatedTxStamp="2018-06-01 10:16:56.0" createdStamp="2018-06-01 10:16:56.0" createdTxStamp="2018-06-01 10:16:56.0"/>
    <SystemProperty systemResourceId="general" systemPropertyId="fio.grid.fetch.limit" systemPropertyValue="1000" description="Fio Grid limit" lastUpdatedStamp="2020-08-31 23:28:17.0" lastUpdatedTxStamp="2020-08-31 23:28:17.0" createdStamp="2020-08-31 23:28:17.0" createdTxStamp="2020-08-31 23:28:17.0"/>
    <SystemProperty systemResourceId="general" systemPropertyId="general.sftp.host" systemPropertyValue="172.31.6.72" lastUpdatedStamp="2022-11-03 02:33:18.0" lastUpdatedTxStamp="2022-11-03 02:33:18.0"/>
    <SystemProperty systemResourceId="general" systemPropertyId="general.sftp.location" systemPropertyValue="/home/icrmbaseftp1/11" lastUpdatedStamp="2022-11-03 02:33:18.0" lastUpdatedTxStamp="2022-11-03 02:33:18.0"/>
    <SystemProperty systemResourceId="general" systemPropertyId="general.sftp.password" systemPropertyValue="!crmftpbase@12345" lastUpdatedStamp="2022-11-03 02:33:18.0" lastUpdatedTxStamp="2022-11-03 02:33:18.0"/>
    <SystemProperty systemResourceId="general" systemPropertyId="general.sftp.port" systemPropertyValue="2200" lastUpdatedStamp="2022-11-03 02:33:18.0" lastUpdatedTxStamp="2022-11-03 02:33:18.0"/>
    <SystemProperty systemResourceId="general" systemPropertyId="general.sftp.user" systemPropertyValue="icrmbaseftp" lastUpdatedStamp="2022-11-03 02:33:18.0" lastUpdatedTxStamp="2022-11-03 02:33:18.0"/>
    <SystemProperty systemResourceId="general" systemPropertyId="is-o365-enabled" systemPropertyValue="N" description="Enable and disable the o365 integration" lastUpdatedStamp="2018-06-01 10:16:56.0" lastUpdatedTxStamp="2018-06-01 10:16:56.0" createdStamp="2018-06-01 10:16:56.0" createdTxStamp="2018-06-01 10:16:56.0"/>
    <SystemProperty systemResourceId="general" systemPropertyId="mail.notifications.enabled" systemPropertyValue="Y" description="mail notifications enabled (Y|N)" lastUpdatedStamp="2018-06-01 10:16:56.0" lastUpdatedTxStamp="2018-06-01 10:16:56.0" createdStamp="2018-06-01 10:16:56.0" createdTxStamp="2018-06-01 10:16:56.0"/>
    <SystemProperty systemResourceId="general" systemPropertyId="mail.smtp.auth.password" description="SMTP Auth password setting" lastUpdatedStamp="2018-06-01 10:16:56.0" lastUpdatedTxStamp="2018-06-01 10:16:56.0" createdStamp="2018-06-01 10:16:56.0" createdTxStamp="2018-06-01 10:16:56.0"/>
    <SystemProperty systemResourceId="general" systemPropertyId="mail.smtp.auth.require" systemPropertyValue="N"/>
    <SystemProperty systemResourceId="general" systemPropertyId="mail.smtp.auth.user" description="SMTP Auth username setting" lastUpdatedStamp="2018-06-01 10:16:56.0" lastUpdatedTxStamp="2018-06-01 10:16:56.0" createdStamp="2018-06-01 10:16:56.0" createdTxStamp="2018-06-01 10:16:56.0"/>
    <SystemProperty systemResourceId="general" systemPropertyId="mail.smtp.port" systemPropertyValue="25" description="Gmail smtp port can be either 465 or 587" lastUpdatedStamp="2018-06-01 10:16:56.0" lastUpdatedTxStamp="2018-06-01 10:16:56.0" createdStamp="2018-06-01 10:16:56.0" createdTxStamp="2018-06-01 10:16:56.0"/>
    <SystemProperty systemResourceId="general" systemPropertyId="mail.smtp.relay.host" systemPropertyValue="groupfio-com.mail.protection.outlook.com" description="the default mail server to use" lastUpdatedStamp="2018-06-01 10:16:56.0" lastUpdatedTxStamp="2018-06-01 10:16:56.0" createdStamp="2018-06-01 10:16:56.0" createdTxStamp="2018-06-01 10:16:56.0"/>
    <SystemProperty systemResourceId="general" systemPropertyId="mail.smtp.sendpartial" systemPropertyValue="Y" description="setting this property to false will abort sending the message" lastUpdatedStamp="2018-06-01 10:16:56.0" lastUpdatedTxStamp="2018-06-01 10:16:56.0" createdStamp="2018-06-01 10:16:56.0" createdTxStamp="2018-06-01 10:16:56.0"/>
    <SystemProperty systemResourceId="general" systemPropertyId="mail.smtp.socketFactory.class" description="JSSE socket factory" lastUpdatedStamp="2018-06-01 10:16:56.0" lastUpdatedTxStamp="2018-06-01 10:16:56.0" createdStamp="2018-06-01 10:16:56.0" createdTxStamp="2018-06-01 10:16:56.0"/>
    <SystemProperty systemResourceId="general" systemPropertyId="mail.smtp.socketFactory.fallback" systemPropertyValue="true" description="Fallback [true|false] determines whether you will allow a non secure connection if you are unable to get a secure one" lastUpdatedStamp="2018-06-01 10:16:56.0" lastUpdatedTxStamp="2018-06-01 10:16:56.0" createdStamp="2018-06-01 10:16:56.0" createdTxStamp="2018-06-01 10:16:56.0"/>
    <SystemProperty systemResourceId="general" systemPropertyId="mail.smtp.socketFactory.port" systemPropertyValue="25" description="Port needs to be the same as mail.smtp.port" lastUpdatedStamp="2018-06-01 10:16:56.0" lastUpdatedTxStamp="2018-06-01 10:16:56.0" createdStamp="2018-06-01 10:16:56.0" createdTxStamp="2018-06-01 10:16:56.0"/>
    <SystemProperty systemResourceId="general" systemPropertyId="mail.smtp.starttls.enable" systemPropertyValue="true" description="Gmail requires StartTLS" lastUpdatedStamp="2018-06-01 10:16:56.0" lastUpdatedTxStamp="2018-06-01 10:16:56.0" createdStamp="2018-06-01 10:16:56.0" createdTxStamp="2018-06-01 10:16:56.0"/>
    <SystemProperty systemResourceId="general" systemPropertyId="mailEngine" systemPropertyValue="GMAIL" description="Type of Mail server using currently" lastUpdatedStamp="2020-10-15 04:33:56.0" lastUpdatedTxStamp="2020-10-15 04:33:56.0" createdStamp="2020-10-12 22:46:58.0" createdTxStamp="2020-10-12 22:46:58.0"/>
    <SystemProperty systemResourceId="general" systemPropertyId="ORGANIZATION_PARTY" description="the default organizationPartyId for used in dropdowns and reports" lastUpdatedStamp="2018-06-01 10:16:56.0" lastUpdatedTxStamp="2018-06-01 10:16:56.0" createdStamp="2018-06-01 10:16:56.0" createdTxStamp="2018-06-01 10:16:56.0"/>
    <SystemProperty systemResourceId="general" systemPropertyId="partner.trackingCodeId.default" description="the default trackingCodeId to use for Partner Managed Tracking Codes" lastUpdatedStamp="2018-06-01 10:16:56.0" lastUpdatedTxStamp="2018-06-01 10:16:56.0" createdStamp="2018-06-01 10:16:56.0" createdTxStamp="2018-06-01 10:16:56.0"/>
    <SystemProperty systemResourceId="general" systemPropertyId="VISUAL_THEME" description="ID of the VisualTheme to use if there is no VISUAL_THEME UserPreference record for the current user (ie default value)" lastUpdatedStamp="2018-06-01 10:16:56.0" lastUpdatedTxStamp="2018-06-01 10:16:56.0" createdStamp="2018-06-01 10:16:56.0" createdTxStamp="2018-06-01 10:16:56.0"/>
  
  	<PretailLoyaltyGlobalParameters parameterId="common.site.key" description="Site Key" value="groupfio.com" storeId="P_INFRA" isActive="Y"/>
	<PretailLoyaltyGlobalParameters parameterId="common.api.key" description="API Key [Generate random key]" value="(jT6*de*uItB" storeId="P_INFRA" isActive="Y"/>
	<PretailLoyaltyGlobalParameters parameterId="webhook.token.expiry.min" description="Token expiry time [min]" value="30" storeId="P_CAMPAIGN" isActive="Y"/>
  
  	<ChannelAccess channelAccessId="GRAVITY_FORM" channelAccessUrl="https://www.groupfio.com/wp-json/gf/v2/forms" merchantName="GroupFIO" password="cs_68f0363c5e3891f563ea42fa47aed38ec00c40f4" userName="ck_48f5fcb6845f2bb1408927b9872a65aac4a6128e"/>
  	<ChannelAccess applicationName="Googleapi Geocode" channelAccessId="GOOGLEAPI_GEOCODE" channelAccessUrl="https://maps.googleapis.com/maps/api/geocode/json?" createdStamp="2021-01-22 17:38:40.0" createdTxStamp="2021-01-22 17:38:40.0" lastUpdatedStamp="2021-01-22 17:38:40.0" lastUpdatedTxStamp="2021-01-22 17:38:40.0" merchantName="GroupFIO" userName="AIzaSyDseN1v_EKLgpwhpq2cgvYSuwBv1YeJYTE"/>
	<ChannelAccess channelAccessId="POSTAL_SERVER" channelAccessUrl="https://emsb.lynxs.ai/api" createdStamp="2024-07-26 03:11:46.0" createdTxStamp="2024-07-26 03:11:46.0" lastUpdatedStamp="2024-07-26 03:11:46.0" lastUpdatedTxStamp="2024-07-26 03:11:46.0" merchantIdentifier="662REEBM2268" merchantName="GroupFIO"/>
	<ChannelAccess applicationName="Ups Configuration" authAccessUrl="https://wwwcie.ups.com/security/v1/oauth/token" channelAccessId="UPS_CONFIG" channelAccessUrl="https://wwwcie.ups.com/api" createdStamp="2024-05-28 21:07:42.0" createdTxStamp="2024-05-28 21:07:42.0" lastUpdatedStamp="2024-05-28 21:07:42.0" lastUpdatedTxStamp="2024-05-28 21:07:42.0" merchantIdentifier="662REEBM2266" merchantName="GroupFIO" password="LVhAU4SBIdesRAK0mllUKrim7iXZSYhSUNAV8z7wvpyykpyyNbnel4G4gm42mU7e" userName="NkGw8H2C3fCLADxAjziwzoCAlxAZtcutJGumQIWWbzAkGT6N"/> 
	<ChannelAccess applicationName="Usps Configuration" channelAccessId="USPS_POSTAL_RC" channelAccessUrl="https://secure.shippingapis.com/ShippingAPI.dll?" createdStamp="2020-12-17 11:18:19.0" createdTxStamp="2020-12-17 11:18:19.0" lastUpdatedStamp="2020-12-17 11:18:19.0" lastUpdatedTxStamp="2020-12-17 11:18:19.0" merchantIdentifier="662REEBM2266" merchantName="GroupFIO"/>
   
    <PretailLoyaltyGlobalParameters parameterId="LEAD_APP_AUTH_URL" description="Lead App Auth Url" value="https://icrmbasestaging.groupfio.com:8443/lead-app/api/lead/v1/verifyLead" storeId="P_LEAD" lastUpdatedStamp="2022-10-26 08:19:32.0" lastUpdatedTxStamp="2022-10-26 08:19:32.0" createdStamp="2022-10-26 08:19:32.0" createdTxStamp="2022-10-26 08:19:32.0" isActive="Y"/>
	<PretailLoyaltyGlobalParameters parameterId="LEAD_APP_KEY" description="Lead App Key" value="h97URZk62OEKVqQKVdsPjSBxXjnVOEqN+sugpgDTJIE=" storeId="P_LEAD" lastUpdatedStamp="2022-10-26 08:19:32.0" lastUpdatedTxStamp="2022-10-26 08:19:32.0" createdStamp="2022-10-26 08:19:32.0" createdTxStamp="2022-10-26 08:19:32.0" isActive="Y"/>
	<PretailLoyaltyGlobalParameters parameterId="LEAD_APP_UPD_URL" description="Lead App Update Url" value="https://icrmbasestaging.groupfio.com:8443/lead-app/api/lead/v1/updateLead" storeId="P_LEAD" lastUpdatedStamp="2022-10-26 08:19:32.0" lastUpdatedTxStamp="2022-10-26 08:19:32.0" createdStamp="2022-10-26 08:19:32.0" createdTxStamp="2022-10-26 08:19:32.0" isActive="Y"/>
	<PretailLoyaltyGlobalParameters parameterId="LEAD_APP_URL" description="Lead App Url" value="https://icrmbasestaging.groupfio.com:8443/lead-app/api/lead/v1/createLead" storeId="P_INFRA" lastUpdatedStamp="2022-10-26 08:19:32.0" lastUpdatedTxStamp="2022-10-26 08:19:32.0" createdStamp="2022-10-26 08:19:32.0" createdTxStamp="2022-10-26 08:19:32.0" isActive="Y"/>
	<PretailLoyaltyGlobalParameters parameterId="LEAD_APP_USER" description="Lead App User" value="icrmapiuser" storeId="P_LEAD" lastUpdatedStamp="2022-10-26 08:19:32.0" lastUpdatedTxStamp="2022-10-26 08:19:32.0" createdStamp="2022-10-26 08:19:32.0" createdTxStamp="2022-10-26 08:19:32.0" isActive="Y"/>
   
    <FioShellScriptServices seqId="1000" serviceName="Generate Loyalty coupons" shellScriptPath="/home/centos/icrm_base_external_app/scripts/generate-lyty-coupons.sh" isEnabled="Y" lastUpdatedStamp="2023-01-27 07:07:07" lastUpdatedTxStamp="2023-01-27 07:07:07" createdStamp="2023-01-27 07:07:07" createdTxStamp="2023-01-27 07:07:07"/>
	<FioShellScriptServices seqId="1001" serviceName="Generate Marketing coupons" shellScriptPath="/home/centos/icrm_base_external_app/scripts/generate-mkt-coupons.sh" isEnabled="Y" lastUpdatedStamp="2023-01-27 07:07:07" lastUpdatedTxStamp="2023-01-27 07:07:07" createdStamp="2023-01-27 07:07:07" createdTxStamp="2023-01-27 07:07:07"/>
	<FioShellScriptServices seqId="1002" serviceName="Generic Coupons Generation" shellScriptPath="/home/centos/icrm_base_external_app/scripts/generic-coupons-generation.sh" isEnabled="Y" lastUpdatedStamp="2023-01-27 07:07:07" lastUpdatedTxStamp="2023-01-27 07:07:07" createdStamp="2023-01-27 07:07:07" createdTxStamp="2023-01-27 07:07:07"/>
   
</entity-engine-xml>